obsidian/__init__.py
obsidian/encryption.py
obsidian/generation.py
obsidian/obsidian.py
obsidian/utils.py
obsn-1.0.2.dist-info/LICENSE
obsn-1.0.2.dist-info/METADATA
obsn-1.0.2.dist-info/WHEEL
obsn-1.0.2.dist-info/top_level.txt
obsn-1.0.2.dist-info/RECORD
