Metadata-Version: 2.1
Name: obsn
Version: 1.0.2
Summary: Making Geometry Dash tool development easier in Python.
Home-page: https://github.com/ObsidianGD/ObsidianPy
Author: SevenworksDev
Author-email: mail@sevenworks.eu.org
License: UNKNOWN
Platform: UNKNOWN
Classifier: Programming Language :: Python :: 3
Classifier: License :: OSI Approved :: MIT License
Classifier: Operating System :: OS Independent
Requires-Python: >=3.8
Requires-Dist: requests
Requires-Dist: plyer
